[
	{"name": "邱雪", "gender": "女"},
	{"name": "徐炳旭", "gender": "男"},
	{"name": "王渊博", "gender": "男"},
	{"name": "刘陶俊楠", "gender": "男"},
	{"name": "白雪", "gender": "女"},
	{"name": "李丹", "gender": "女"},
	{"name": "屈凡", "gender": "女"},
	{"name": "刘海艳", "gender": "女"},
	{"name": "张倩", "gender": "女"},
	{"name": "付红", "gender": "女"},
	{"name": "李优优", "gender": "女"},
	{"name": "谭艺冰", "gender": "女"},
	{"name": "廖安英", "gender": "女"},
	{"name": "段锦梦", "gender": "女"},
	{"name": "马睿祺", "gender": "男"},
	{"name": "安粉", "gender": "女"},
	{"name": "刘小玥", "gender": "女"},
	{"name": "卓越", "gender": "女"},
	{"name": "夏雨", "gender": "女"},
	{"name": "赵彤", "gender": "女"},
	{"name": "赵悦妮", "gender": "女"},
	{"name": "李婷婷", "gender": "女"},
	{"name": "薛佳瑶", "gender": "女"}
]